buildsql/__init__.py
buildsql/base.py
buildsql/delete_from.py
buildsql/insert_into.py
buildsql/operators.py
buildsql/py.typed
buildsql/select.py
buildsql/update.py
buildsql/utils.py
buildsql-0.0.2.dist-info/METADATA
buildsql-0.0.2.dist-info/WHEEL
buildsql-0.0.2.dist-info/top_level.txt
buildsql-0.0.2.dist-info/RECORD
