Metadata-Version: 2.4
Name: buildsql
Version: 0.0.2
Summary: Add your description here
License-Expression: Apache-2.0
Requires-Python: >=3.13
Requires-Dist: sqlalchemy>=2.0.44
